{
  "cta": {
    "main": {
      "url": "https://bouwzaken.spp.co/order/funda_proberen",
      "text": "Gratis 1 foto proberen!",
      "target": "_blank",
      "description": "Main hero CTA button"
    },
    "inloggen": {
      "url": "https://bouwzaken.spp.co/portal/dashboard",
      "text": "Inloggen",
      "target": "_blank",
      "description": "Login link for existing users"
    }
  },
  "pricing": {
    "starter": {
      "url": "https://bouwzaken.spp.co/order/makelaar",
      "text": "Begin Nu",
      "target": "_blank",
      "description": "Starter plan signup"
    },
    "business": {
      "url": "https://bouwzaken.spp.co/order/makelaar", 
      "text": "Begin Nu",
      "target": "_blank",
      "description": "Business plan signup (most popular)"
    },
    "premium": {
      "url": "https://bouwzaken.spp.co/order/makelaar",
      "text": "Begin Nu", 
      "target": "_blank",
      "description": "Premium plan signup"
    }
  },
  "external": {
    "learn_more": {
      "url": "",
      "text": "Meer informatie",
      "target": "_blank",
      "description": "General information page"
    },
    "helpdesk": {
      "url": "https://bouwzaken.spp.co/contact/helpdesk",
      "text": "Klantenservice",
      "target": "_blank", 
      "description": "Customer support and help"
    }
  }
}
